COPYING
MANIFEST.in
NEWS.rst
README
ols-run-tests2
setup.py
olstests/__init__.py
olstests/assertions.py
olstests/features.py
olstests/filters.py
olstests/fixtures.py
olstests/loaders.py
olstests/matchers.py
olstests/results.py
olstests/runners.py
olstests/scenarii.py
olstests/styles.py
olstests/suites.py
olstests/walkers.py
olstests.egg-info/PKG-INFO
olstests.egg-info/SOURCES.txt
olstests.egg-info/dependency_links.txt
olstests.egg-info/requires.txt
olstests.egg-info/top_level.txt
olstests/tests/__init__.py
olstests/tests/test_assertions.py
olstests/tests/test_features.py
olstests/tests/test_filters.py
olstests/tests/test_fixtures.py
olstests/tests/test_loaders.py
olstests/tests/test_matchers.py
olstests/tests/test_results.py
olstests/tests/test_runners.py
olstests/tests/test_scenarii.py
olstests/tests/test_styles.py
olstests/tests/test_suites.py
olstests/tests/test_walkers.py