Metadata-Version: 1.0
Name: olstests
Version: 1.0.0
Summary: Online Services test tools.
Home-page: https://launchpad.net/ols-tests
Author: Vincent Ladeuil
Author-email: vila+ols@canonical.com
License: GPLv3
Platform: UNKNOWN
